[
  {
    "model": "requirements.RequirementTemplate",
    "pk": 1,
    "fields": {
      "key": "passport_valid",
      "title": "Valid Passport",
      "description": "Upload a scan of your passport. Must be valid for at least 6 months beyond your program start date.",
      "scope": "global",
      "requirement_type": "document",
      "verification_level": "official",
      "official_source_url": "https://www.gov.uk/passport-application",
      "official_source_label": "Government Passport Office",
      "min_days_before_deadline": 180,
      "estimated_effort_hours": 1.0,
      "document_rules": {
        "format": "PDF or JPG",
        "details": "First page and signature page",
        "max_size_mb": 5
      },
      "reusable_across_targets": true,
      "post_offer_only": false,
      "dependency_keys": []
    }
  },
  {
    "model": "requirements.RequirementTemplate",
    "pk": 2,
    "fields": {
      "key": "ielts_academic",
      "title": "IELTS Academic Test",
      "description": "Take IELTS Academic. Most universities require 6.5+ overall with no band below 6.0.",
      "scope": "global",
      "requirement_type": "test_score",
      "verification_level": "vendor",
      "official_source_url": "https://www.ielts.org/for-organisations/recognising-organisations",
      "official_source_label": "IELTS Organization",
      "min_days_before_deadline": 60,
      "estimated_effort_hours": 3.0,
      "document_rules": {
        "format": "Test Report Form Number",
        "how_to": "Register at britishcouncil.kz",
        "min_score": {
          "overall": 6.5,
          "bands": {"reading": 6.0, "writing": 6.0, "listening": 6.0, "speaking": 6.0}
        }
      },
      "reusable_across_targets": true,
      "post_offer_only": false,
      "dependency_keys": []
    }
  },
  {
    "model": "requirements.RequirementTemplate",
    "pk": 3,
    "fields": {
      "key": "toefl_ibit",
      "title": "TOEFL iBT Test",
      "description": "Take TOEFL iBT. Most universities require 90+ overall with minimum section scores.",
      "scope": "global",
      "requirement_type": "test_score",
      "verification_level": "vendor",
      "official_source_url": "https://www.ets.org/toefl",
      "official_source_label": "ETS TOEFL",
      "min_days_before_deadline": 60,
      "estimated_effort_hours": 3.0,
      "document_rules": {
        "format": "Test Report Form Number",
        "how_to": "Register at ets.org/toefl",
        "min_score": {
          "overall": 90,
          "sections": {"reading": 20, "writing": 20, "listening": 20, "speaking": 20}
        }
      },
      "reusable_across_targets": true,
      "post_offer_only": false,
      "dependency_keys": []
    }
  },
  {
    "model": "requirements.RequirementTemplate",
    "pk": 4,
    "fields": {
      "key": "academic_transcripts",
      "title": "Academic Transcripts",
      "description": "Official academic transcripts from your previous institution showing all courses and grades.",
      "scope": "global",
      "requirement_type": "document",
      "verification_level": "official",
      "official_source_url": "https://www.university.edu/records",
      "official_source_label": "University Registrar",
      "min_days_before_deadline": 90,
      "estimated_effort_hours": 5.0,
      "document_rules": {
        "format": "PDF",
        "details": "Official transcript with registrar signature and seal",
        "notarized": false,
        "translation_required": true
      },
      "reusable_across_targets": true,
      "post_offer_only": false,
      "dependency_keys": []
    }
  },
  {
    "model": "requirements.RequirementTemplate",
    "pk": 5,
    "fields": {
      "key": "cv_resume",
      "title": "CV/Resume",
      "description": "Current curriculum vitae or resume detailing your education, work experience, skills, and achievements.",
      "scope": "global",
      "requirement_type": "document",
      "verification_level": "assumed",
      "official_source_url": null,
      "official_source_label": null,
      "min_days_before_deadline": 30,
      "estimated_effort_hours": 3.0,
      "document_rules": {
        "format": "PDF",
        "max_length_pages": 2
      },
      "reusable_across_targets": true,
      "post_offer_only": false,
      "dependency_keys": []
    }
  },
  {
    "model": "requirements.RequirementTemplate",
    "pk": 6,
    "fields": {
      "key": "personal_statement",
      "title": "Personal Statement",
      "description": "A statement explaining your academic interests, career goals, and why you're applying to these programs.",
      "scope": "global",
      "requirement_type": "essay",
      "verification_level": "assumed",
      "official_source_url": null,
      "official_source_label": null,
      "min_days_before_deadline": 21,
      "estimated_effort_hours": 8.0,
      "document_rules": {
        "format": "PDF",
        "length": "1-2 pages"
      },
      "evaluation_criteria": [
        "Clarity of academic motivation",
        "Career alignment",
        "Writing quality",
        "Specific examples"
      ],
      "reusable_across_targets": true,
      "post_offer_only": false,
      "dependency_keys": []
    }
  },
  {
    "model": "requirements.RequirementTemplate",
    "pk": 7,
    "fields": {
      "key": "recommendation_letters",
      "title": "Letters of Recommendation",
      "description": "2-3 letters of recommendation from teachers or professors who can speak to your academic abilities.",
      "scope": "global",
      "requirement_type": "other",
      "verification_level": "assumed",
      "official_source_url": null,
      "official_source_label": null,
      "min_days_before_deadline": 45,
      "estimated_effort_hours": 2.0,
      "document_rules": {
        "format": "Online form or PDF",
        "count": 2,
        "max_count": 3
      },
      "reusable_across_targets": true,
      "post_offer_only": false,
      "dependency_keys": []
    }
  },
  {
    "model": "requirements.RequirementTemplate",
    "pk": 8,
    "fields": {
      "key": "portfolio",
      "title": "Portfolio",
      "description": "Collection of your best creative work demonstrating your skills and experience.",
      "scope": "global",
      "requirement_type": "other",
      "verification_level": "assumed",
      "official_source_url": null,
      "official_source_label": null,
      "min_days_before_deadline": 30,
      "estimated_effort_hours": 20.0,
      "document_rules": {
        "format": "PDF or online link",
        "max_size_mb": 20,
        "max_pages": 20
      },
      "evaluation_criteria": [
        "Technical skills",
        "Creativity",
        "Variety of work",
        "Presentation quality"
      ],
      "reusable_across_targets": true,
      "post_offer_only": false,
      "dependency_keys": [],
      "applies_to_programs": ["architecture", "design", "art", "fashion"]
    }
  }
]
